tests/__init__.py
tests/test_comment_class.py
tests/test_fund_class.py
tests/test_model_functions.py
tests/test_post_class.py
tests/test_selector_class.py
tests/test_stock_class.py
tests/test_user_class.py
tests/test_utils_module.py
xueqiu/__init__.py
xueqiu/__main__.py
xueqiu/api.py
xueqiu/baidu.py
xueqiu/model.py
xueqiu/sheet.py
xueqiu/utils.py
xueqiu-0.1.3.dist-info/LICENSE
xueqiu-0.1.3.dist-info/METADATA
xueqiu-0.1.3.dist-info/WHEEL
xueqiu-0.1.3.dist-info/top_level.txt
xueqiu-0.1.3.dist-info/RECORD
